<values>
<value name="dumpAreaDepth"
type="string">40</value>
<value name="printerType"
type="int">2</value>
<value name="port"
type="string">/dev/ttyACM0</value>
<value name="gcodeScript3"
type="string"/>
<value name="numExtruder"
type="int">1</value>
<value name="numFans"
type="int">1</value>
<value name="showPrinterBottom"
type="int">1</value>
<value name="receiveCacheSize"
type="int">127</value>
<value name="printerXMin"
type="string">-135</value>
<value name="disposeX"
type="string">0</value>
<value name="zhomepos"
type="string">0</value>
<value name="rts"
type="int">0</value>
<value name="transferProtocol"
type="int">0</value>
<value name="printerYMin"
type="string">-135</value>
<value name="gcodeScript5Name"
type="string">Script 5</value>
<value name="gcodeScript5"
type="string"/>
<value name="checkTemp"
type="int">1</value>
<value name="disableHeatedBetAfterJob"
type="int">1</value>
<value name="disposeY"
type="string">0</value>
<value name="gcodeScript1"
type="string">; Rostock Max Tower end-stop calibration script
G28
G1 Z0.2 F15000
G4 S5
G1 X-77.94 Y-45 Z0.2 F2000
G4 S5
G1 X0 Y0 Z0.2
G1 X77.94 Y-45 Z0.2
G4 S5
G1 X0 Y0 Z0.2
G1 Y90 Z0.2
G4 S5
G1 X0 Y0 Z0.2
</value>
<value name="rostockHeight"
type="string">340</value>
<value name="maxBedTemp"
type="int">90</value>
<value name="printerXMax"
type="string">135</value>
<value name="runFilterEverySlice"
type="int">0</value>
<value name="defaultHeatedBedTemp"
type="int">55</value>
<value name="resetOnEmergency"
type="int">2</value>
<value name="dtr"
type="int">0</value>
<value name="InvertYAxisControl"
type="int">0</value>
<value name="printModel3"
type="string">No STL selected</value>
<value name="maxExtruderTemp"
type="int">280</value>
<value name="printAreaHeight"
type="string">340</value>
<value name="checkTempInterval"
type="int">3</value>
<value name="manualExtrusionSpeedFast"
type="string">20</value>
<value name="hasMixingExtruder"
type="int">0</value>
<value name="logM105"
type="int">0</value>
<value name="sendETADispay"
type="int">1</value>
<value name="gcodeKill"
type="string"/>
<value name="disposeZ"
type="string">0</value>
<value name="printerBedLeft"
type="string">-135</value>
<value name="gcodeScript3Name"
type="string">Script 3</value>
<value name="printAreaDepth"
type="string">270</value>
<value name="gcodePrepend"
type="string"/>
<value name="InvertXAxisControl"
type="int">0</value>
<value name="gcodeScript1Name"
type="string">Script 1</value>
<value name="manualReatrctionSpeed"
type="string">30</value>
<value name="PrinterHasSD"
type="int">1</value>
<value name="cncZTop"
type="string">0</value>
<value name="InvertZAxisControl"
type="int">0</value>
<value name="rostockRadius"
type="string">135</value>
<value name="defaultExtruderTemp"
type="int">200</value>
<value name="printAreaWidth"
type="string">270</value>
<value name="dumpAreaLeft"
type="string">125</value>
<value name="travelFeedrate"
type="string">4800</value>
<value name="yhomepos"
type="string">0</value>
<value name="filterPath"
type="string">yourFilter #in #out</value>
<value name="disableMotorsAfterJob"
type="int">1</value>
<value name="gcodeScript2"
type="string"/>
<value name="dumpAreaFront"
type="string">0</value>
<value name="printModel2"
type="string">/home/jasonh/work/3dp/RepetierHost/data/models/DemoPrinter_2.stl</value>
<value name="firmwareType"
type="int">0</value>
<value name="gcodeScript4"
type="string"/>
<value name="pingPong"
type="int">0</value>
<value name="gcodeScript2Name"
type="string">Script 2</value>
<value name="printerBedFront"
type="string">-135</value>
<value name="addPrintingTime"
type="string">8</value>
<value name="xhomepos"
type="string">0</value>
<value name="slicerSelection"
type="string">curaengine</value>
<value name="maxVolumePerSecond"
type="string">12</value>
<value name="zAxisFeedrate"
type="string">100</value>
<value name="printerYMax"
type="string">135</value>
<value name="showPrintModel"
type="int">0</value>
<value name="resetOnConnect"
type="int">2</value>
<value name="disableExtruderAfterJob"
type="int">1</value>
<value name="gcodePause"
type="string"/>
<value name="communicationTimeout"
type="int">40</value>
<value name="dumpAreaWidth"
type="string">22</value>
<value name="gcodeContinue"
type="string"/>
<value name="gcodeAppend"
type="string"/>
<value name="printModel3Color"
type="int">-8388652</value>
<value name="printModel2Color"
type="int">-16777216</value>
<value name="printModel1"
type="string">/home/jasonh/work/3dp/RepetierHost/data/models/DemoPrinter_1.stl</value>
<value name="baud"
type="string">250000</value>
<value name="printModel1Color"
type="int">-2894893</value>
<value name="connector"
type="string">SerialConnector</value>
<value name="goDisposeAfterJob"
type="int">0</value>
<value name="FlipXY"
type="int">0</value>
<value name="gcodeScript4Name"
type="string">Script 4</value>
<value name="manualExtrusionSpeed"
type="string">2</value>
</values>
